latch_aws/__init__.py
latch_aws/aws.py
latch_aws/client_pool.py
latch_aws/py.typed
latch_aws-0.2.11.dist-info/METADATA
latch_aws-0.2.11.dist-info/WHEEL
latch_aws-0.2.11.dist-info/licenses/LICENSE
latch_aws-0.2.11.dist-info/RECORD
