Metadata-Version: 2.4
Name: latch-aws
Version: 0.2.11
Summary: Traced and managed aws resources
Author-email: maximsmol <max@latch.bio>
License: CC0-1.0
License-File: LICENSE
Requires-Python: >=3.11.0
Requires-Dist: aiobotocore[s3]>=2.4.2
Requires-Dist: latch-data-validation>=0.1.3
Requires-Dist: latch-o11y>=0.1.4
Requires-Dist: opentelemetry-sdk>=1.15.0
Requires-Dist: types-aiobotocore[ec2,ecr,s3,secretsmanager,sts]>=2.4.2
